booth.v
module booth (
    input clk, rst, load,
    input signed [7:0] a, b,
    output reg signed[15:0] product,
    output reg done
);

    reg [7:0]M, Q, A;
    reg signed [8:0]M_bar;
    reg Q_1;
    reg [2:0]count;


    reg [2:0]state;
    parameter IDLE = 3'b000,
                LOAD = 3'b001,
                COMPARE = 3'b010,
                ZERO_ONE = 3'b011,
                ONE_ZERO = 3'b100,
                SHIFT = 3'b101,
                DONE = 3'b110;

    always @(posedge clk or posedge rst) begin
        if(rst) begin
            state <= IDLE;
            A <= 8'b00;
            M <= 8'b00;
            M_bar <= 9'b00;
            Q <= 8'b00;
            Q_1 <= 1'b0;
            done <= 1'b0;
        end else begin
            case(state)
                IDLE: begin
                    done <= 1'b0;
                    if(load)begin
                        state <= LOAD;
                    end
                end
                LOAD: begin
                    count <= 0;
                    A <= 8'b00;
                    M <= a;
                    Q <= b;
                    Q_1 <= 1'b0;
                    M_bar <= (~a) + 1'b1;
                    state <= COMPARE;
                end
                COMPARE: begin
                    if({Q[0],Q_1} == 2'b01) state <= ZERO_ONE;
                    else if({Q[0],Q_1} == 2'b10) state <= ONE_ZERO;
                    else state <= SHIFT;
                end
                ZERO_ONE: begin
                    A <= A + M;
                    state <= SHIFT;
                end
                ONE_ZERO: begin
                    A <= A + M_bar;
                    state <= SHIFT;
                end
                SHIFT: begin
                    {A,Q,Q_1} <= {A[7],A[7:1],A[0],Q[7:1],Q[0]};
                    if(count == 7)state <= DONE;
                    else begin
                        count <= count + 1;
                        state <= COMPARE;
                    end
                end
                DONE: begin
                    product <= {A, Q};
                    done <= 1'b1;
                    state <= IDLE;
                end
            endcase
        end
    end   
endmodule

booth_tb.v
`timescale 1ps/1ps
`include "booth.v"

module booth_tb();
    reg clk, rst, load;
    reg signed [7:0]a, b;

    wire signed [15:0]product;
    wire done;

    booth DUT(.clk(clk), .rst(rst), .load(load), .a(a), .b(b), .product(product), .done(done));

    initial begin
        clk = 0; rst = 1; load = 0;
        #5 rst = 0;

        a=10; b=-2;
        load = 1; #10 load = 0;
        wait(done); 
        #10
        a=-8; b=4; 
        load = 1; #10 load = 0;
        wait(done); 
        #10
        a=-5; b=-2;
        load = 1; #10 load = 0;
        wait(done);
        #10
        a=3; b=7;
        load = 1; #10 load = 0;
        wait(done);

        #100
        $finish;
    end

    initial begin
        $dumpfile("booth.vcd");
        $dumpvars(0,booth_tb);

        // $monitor("clk=%d  A=%d  B=%d  Product=%d",clk, a, b, product);
    end
    always @(posedge done) begin
        $display("✅ DONE: A=%d  B=%d  Product=%d", a, b, product);
    end
    always #5 clk = ~clk; //10 - time period

endmodule

booth.vcd
$date
	Thu Nov 06 22:11:38 2025
$end
$version
	Icarus Verilog
$end
$timescale
	1ps
$end
$scope module booth_tb $end
$var wire 16 ! product [15:0] $end
$var wire 1 " done $end
$var reg 8 # a [7:0] $end
$var reg 8 $ b [7:0] $end
$var reg 1 % clk $end
$var reg 1 & load $end
$var reg 1 ' rst $end
$scope module DUT $end
$var wire 8 ( a [7:0] $end
$var wire 8 ) b [7:0] $end
$var wire 1 % clk $end
$var wire 1 & load $end
$var wire 1 ' rst $end
$var parameter 3 * COMPARE $end
$var parameter 3 + DONE $end
$var parameter 3 , IDLE $end
$var parameter 3 - LOAD $end
$var parameter 3 . ONE_ZERO $end
$var parameter 3 / SHIFT $end
$var parameter 3 0 ZERO_ONE $end
$var reg 8 1 A [7:0] $end
$var reg 8 2 M [7:0] $end
$var reg 9 3 M_bar [8:0] $end
$var reg 8 4 Q [7:0] $end
$var reg 1 5 Q_1 $end
$var reg 3 6 count [2:0] $end
$var reg 1 " done $end
$var reg 16 7 product [15:0] $end
$var reg 3 8 state [2:0] $end
$upscope $end
$upscope $end
$enddefinitions $end
$comment Show the parameter values. $end
$dumpall
b11 0
b101 /
b100 .
b1 -
b0 ,
b110 +
b10 *
$end
#0
$dumpvars
b0 8
bx 7
bx 6
05
b0 4
b0 3
b0 2
b0 1
bx )
bx (
1'
0&
0%
bx $
bx #
0"
bx !
$end
#5
b1 8
1%
1&
b11111110 $
b11111110 )
b1010 #
b1010 (
0'
#10
0%
#15
b10 8
b111110110 3
b11111110 4
b1010 2
b0 6
1%
0&
#20
0%
#25
b101 8
1%
#30
0%
#35
b10 8
b1 6
b1111111 4
1%
#40
0%
#45
b100 8
1%
#50
0%
#55
b101 8
b11110110 1
1%
#60
0%
#65
b10 8
b10 6
b11111011 1
b111111 4
15
1%
#70
0%
#75
b101 8
1%
#80
0%
#85
b10 8
b11 6
b11111101 1
b10011111 4
1%
#90
0%
#95
b101 8
1%
#100
0%
#105
b10 8
b100 6
b11111110 1
b11001111 4
1%
#110
0%
#115
b101 8
1%
#120
0%
#125
b10 8
b101 6
b11111111 1
b1100111 4
1%
#130
0%
#135
b101 8
1%
#140
0%
#145
b10 8
b110 6
b10110011 4
1%
#150
0%
#155
b101 8
1%
#160
0%
#165
b10 8
b111 6
b11011001 4
1%
#170
0%
#175
b101 8
1%
#180
0%
#185
b110 8
b11101100 4
1%
#190
0%
#195
b0 8
1"
b1111111111101100 !
b1111111111101100 7
1%
#200
0%
#205
b1 8
0"
1%
1&
b100 $
b100 )
b11111000 #
b11111000 (
#210
0%
#215
b10 8
b100001000 3
05
b100 4
b11111000 2
b0 1
b0 6
1%
0&
#220
0%
#225
b101 8
1%
#230
0%
#235
b10 8
b1 6
b10 4
1%
#240
0%
#245
b101 8
1%
#250
0%
#255
b10 8
b10 6
b1 4
1%
#260
0%
#265
b100 8
1%
#270
0%
#275
b101 8
b1000 1
1%
#280
0%
#285
b10 8
b11 6
b100 1
b0 4
15
1%
#290
0%
#295
b11 8
1%
#300
0%
#305
b101 8
b11111100 1
1%
#310
0%
#315
b10 8
b100 6
b11111110 1
05
1%
#320
0%
#325
b101 8
1%
#330
0%
#335
b10 8
b101 6
b11111111 1
1%
#340
0%
#345
b101 8
1%
#350
0%
#355
b10 8
b110 6
b10000000 4
1%
#360
0%
#365
b101 8
1%
#370
0%
#375
b10 8
b111 6
b11000000 4
1%
#380
0%
#385
b101 8
1%
#390
0%
#395
b110 8
b11100000 4
1%
#400
0%
#405
b0 8
1"
b1111111111100000 !
b1111111111100000 7
1%
#410
0%
#415
b1 8
0"
1%
1&
b11111110 $
b11111110 )
b11111011 #
b11111011 (
#420
0%
#425
b10 8
b100000101 3
b11111110 4
b11111011 2
b0 1
b0 6
1%
0&
#430
0%
#435
b101 8
1%
#440
0%
#445
b10 8
b1 6
b1111111 4
1%
#450
0%
#455
b100 8
1%
#460
0%
#465
b101 8
b101 1
1%
#470
0%
#475
b10 8
b10 6
b10 1
b10111111 4
15
1%
#480
0%
#485
b101 8
1%
#490
0%
#495
b10 8
b11 6
b1 1
b1011111 4
1%
#500
0%
#505
b101 8
1%
#510
0%
#515
b10 8
b100 6
b0 1
b10101111 4
1%
#520
0%
#525
b101 8
1%
#530
0%
#535
b10 8
b101 6
b1010111 4
1%
#540
0%
#545
b101 8
1%
#550
0%
#555
b10 8
b110 6
b101011 4
1%
#560
0%
#565
b101 8
1%
#570
0%
#575
b10 8
b111 6
b10101 4
1%
#580
0%
#585
b101 8
1%
#590
0%
#595
b110 8
b1010 4
1%
#600
0%
#605
b0 8
1"
b1010 !
b1010 7
1%
#610
0%
#615
b1 8
0"
1%
1&
b111 $
b111 )
b11 #
b11 (
#620
0%
#625
b10 8
b111111101 3
05
b111 4
b11 2
b0 6
1%
0&
#630
0%
#635
b100 8
1%
#640
0%
#645
b101 8
b11111101 1
1%
#650
0%
#655
b10 8
b1 6
b11111110 1
b10000011 4
15
1%
#660
0%
#665
b101 8
1%
#670
0%
#675
b10 8
b10 6
b11111111 1
b1000001 4
1%
#680
0%
#685
b101 8
1%
#690
0%
#695
b10 8
b11 6
b10100000 4
1%
#700
0%
#705
b11 8
1%
#710
0%
#715
b101 8
b10 1
1%
#720
0%
#725
b10 8
b100 6
b1 1
b1010000 4
05
1%
#730
0%
#735
b101 8
1%
#740
0%
#745
b10 8
b101 6
b0 1
b10101000 4
1%
#750
0%
#755
b101 8
1%
#760
0%
#765
b10 8
b110 6
b1010100 4
1%
#770
0%
#775
b101 8
1%
#780
0%
#785
b10 8
b111 6
b101010 4
1%
#790
0%
#795
b101 8
1%
#800
0%
#805
b110 8
b10101 4
1%
#810
0%
#815
b0 8
1"
b10101 !
b10101 7
1%
#820
0%
#825
0"
1%
